zermelo_api/__init__.py
zermelo_api/src/__init__.py
zermelo_api/src/_config.py
zermelo_api/src/_credentials.py
zermelo_api/src/_io_json.py
zermelo_api/src/_time_utils.py
zermelo_api/src/_zermelo_api.py
zermelo_api/src/_zermelo_collection.py
zermelo_api/src/appointments.py
zermelo_api/src/branches.py
zermelo_api/src/config.py
zermelo_api/src/credentials.py
zermelo_api/src/groepen.py
zermelo_api/src/install.py
zermelo_api/src/io_json.py
zermelo_api/src/leerjaren.py
zermelo_api/src/lesgroepen.py
zermelo_api/src/logger.py
zermelo_api/src/lokalen.py
zermelo_api/src/schoolyears.py
zermelo_api/src/time_utils.py
zermelo_api/src/users.py
zermelo_api/src/vakdoclok.py
zermelo_api/src/vakken.py
zermelo_api/src/vaklessen.py
zermelo_api/src/vaklokdoc.py
zermelo_api/src/zermelo_api.py
zermelo_api/src/zermelo_collection.py
zermelo_api_vogk-1.3.3.dist-info/LICENSE
zermelo_api_vogk-1.3.3.dist-info/METADATA
zermelo_api_vogk-1.3.3.dist-info/WHEEL
zermelo_api_vogk-1.3.3.dist-info/top_level.txt
zermelo_api_vogk-1.3.3.dist-info/RECORD
