Metadata-Version: 2.1
Name: zermelo_api_vogk
Version: 1.3.3
Summary: A small module to create a Zermelo accesstoken and put some data from Zermelo in dataclasses
Home-page: https://github.com/KlaasVogel/zermelo_api_vogk
Author: Klaas Vogel
Author-email: zermelo_api@klaasvogel.nl
License: MIT
Classifier: License :: OSI Approved :: MIT License
Classifier: Programming Language :: Python :: 3.12
Classifier: Operating System :: OS Independent
Requires-Python: >=3.12
License-File: LICENSE
Requires-Dist: aiohttp
Provides-Extra: dev
